{"lastUsed":1559297245399,"path":"\/home\/sandy_143\/eclipse-workspace","projectCount":4,"recentFiles":[{"path":"\/Jdbc\/WebContent","parentWorkspace":"\/home\/sandy_143\/eclipse-workspace","name":"index.jsp","lastModified":1559245025034,"locationURI":"file:\/home\/sandy_143\/eclipse-workspace\/Jdbc\/WebContent\/index.jsp"},{"path":"\/JdbcFirst\/WebContent","parentWorkspace":"\/home\/sandy_143\/eclipse-workspace","name":"index0.jsp","lastModified":1559296388567,"locationURI":"file:\/home\/sandy_143\/eclipse-workspace\/JdbcFirst\/WebContent\/index0.jsp"},{"path":"\/JdbcFirst\/WebContent","parentWorkspace":"\/home\/sandy_143\/eclipse-workspace","name":"index1.jsp","lastModified":1559295821121,"locationURI":"file:\/home\/sandy_143\/eclipse-workspace\/JdbcFirst\/WebContent\/index1.jsp"},{"path":"\/myProject\/WebContent","parentWorkspace":"\/home\/sandy_143\/eclipse-workspace","name":"welcome.jsp","lastModified":1559239975544,"locationURI":"file:\/home\/sandy_143\/Documents\/project\/WebContent\/welcome.jsp"},{"path":"\/myProject\/WebContent\/WEB-INF","parentWorkspace":"\/home\/sandy_143\/eclipse-workspace","name":"web.xml","lastModified":1559223495363},{"path":"\/myProject\/WebContent","parentWorkspace":"\/home\/sandy_143\/eclipse-workspace","name":"login.jsp","lastModified":1559222510054,"locationURI":"file:\/home\/sandy_143\/Documents\/project\/WebContent\/login.jsp"},{"path":"\/JdbcFirst\/src\/Insert","parentWorkspace":"\/home\/sandy_143\/eclipse-workspace","name":"Data.java","lastModified":1559297180758,"locationURI":"file:\/home\/sandy_143\/eclipse-workspace\/JdbcFirst\/src\/Insert\/Data.java"},{"path":"\/Jdbc\/WebContent","parentWorkspace":"\/home\/sandy_143\/eclipse-workspace","name":"index1.jsp","lastModified":1559245024254,"locationURI":"file:\/home\/sandy_143\/eclipse-workspace\/Jdbc\/WebContent\/index1.jsp"},{"path":"\/myProject\/WebContent","parentWorkspace":"\/home\/sandy_143\/eclipse-workspace","name":"index.html","lastModified":1559223348441,"locationURI":"file:\/home\/sandy_143\/Documents\/project\/WebContent\/index.html"},{"path":"\/Jdbc\/WebContent","parentWorkspace":"\/home\/sandy_143\/eclipse-workspace","name":"index2.jsp","lastModified":1559296531586,"locationURI":"file:\/home\/sandy_143\/eclipse-workspace\/Jdbc\/WebContent\/index2.jsp"},{"path":"\/myProject\/src\/myProject","parentWorkspace":"\/home\/sandy_143\/eclipse-workspace","name":"JdbcDao.java","lastModified":1559239835492,"locationURI":"file:\/home\/sandy_143\/Documents\/project\/src\/myProject\/JdbcDao.java"},{"path":"\/myProject\/src\/myProject","parentWorkspace":"\/home\/sandy_143\/eclipse-workspace","name":"Login.java","lastModified":1559239975544,"locationURI":"file:\/home\/sandy_143\/Documents\/project\/src\/myProject\/Login.java"}]}